{"commitInfo":{"timestamp":1773842811996,"operation":"WRITE","operationParameters":{"mode":"Overwrite"},"engineInfo":"delta-rs:py-1.5.0","clientVersion":"delta-rs.py-1.5.0","operationMetrics":{"execution_time_ms":20,"num_added_files":1,"num_added_rows":50000,"num_partitions":0,"num_removed_files":2}}}
{"remove":{"path":"part-00000-a2945ba9-64a8-4213-928e-430a80a63464-c000.snappy.parquet","dataChange":true,"deletionTimestamp":1773842811975,"extendedFileMetadata":true,"partitionValues":{},"size":1519536}}
{"remove":{"path":"part-00000-d3aceab8-edd2-43cc-a4fa-6d39b93cd1f0-c000.snappy.parquet","dataChange":true,"deletionTimestamp":1773842811975,"extendedFileMetadata":true,"partitionValues":{},"size":2457054}}
{"add":{"path":"part-00000-315c6fc3-0104-44f4-ad1f-ce0cd99a8390-c000.snappy.parquet","partitionValues":{},"size":2457054,"modificationTime":1773842811996,"dataChange":true,"stats":"{\"numRecords\":50000,\"minValues\":{\"ulica\":\"-\",\"obec\":\"'S-HERTOGENBOSCH, NL\",\"nazov\":\"\\\" A.G.S.K. spol. s r.o.\\\"\",\"psc\":\"-\",\"id\":1,\"nazov_normalized\":\"&brain\",\"suma\":170.03},\"maxValues\":{\"obec\":\"ПОЛША, WARSZAWA, PL\",\"id\":50000,\"nazov\":\"NaviShop s.r.o.\",\"nazov_normalized\":\"žalár\",\"suma\":38948032.81,\"psc\":\"XBX1093\",\"ulica\":\"ΣΟΦΟΥΛΗ 28\"},\"nullCount\":{\"nazov_normalized\":0,\"ulica\":602,\"suma\":0,\"psc\":227,\"obec\":0,\"nazov\":0,\"id\":0}}","tags":null,"baseRowId":null,"defaultRowCommitVersion":null,"clusteringProvider":null}}